faircom_jsonapi/__init__.py
faircom_jsonapi/client.py
faircom_jsonapi/dbapi.py
faircom_jsonapi/sqlalchemy_dialect.py
sqlalchemy_faircom-0.1.19.dist-info/licenses/LICENSE
sqlalchemy_faircom-0.1.19.dist-info/METADATA
sqlalchemy_faircom-0.1.19.dist-info/WHEEL
sqlalchemy_faircom-0.1.19.dist-info/entry_points.txt
sqlalchemy_faircom-0.1.19.dist-info/top_level.txt
sqlalchemy_faircom-0.1.19.dist-info/RECORD
