Metadata-Version: 2.4
Name: sqlalchemy-faircom
Version: 0.1.19
Summary: SQLAlchemy dialect for FairCom Database via JSON API
Author: Custom Implementation
Author-email: FairCom Corporation <support@faircom.com>
License: MIT
Project-URL: Homepage, https://github.com/toddstoffel/sqlalchemy-faircom
Project-URL: Documentation, https://github.com/toddstoffel/sqlalchemy-faircom
Project-URL: Repository, https://github.com/toddstoffel/sqlalchemy-faircom
Project-URL: Bug Tracker, https://github.com/toddstoffel/sqlalchemy-faircom/issues
Keywords: sqlalchemy,faircom,database,json-api,db-api
Classifier: Development Status :: 4 - Beta
Classifier: Intended Audience :: Developers
Classifier: Programming Language :: Python :: 3
Classifier: Programming Language :: Python :: 3.7
Classifier: Programming Language :: Python :: 3.8
Classifier: Programming Language :: Python :: 3.9
Classifier: Programming Language :: Python :: 3.10
Classifier: Programming Language :: Python :: 3.11
Classifier: Programming Language :: Python :: 3.12
Classifier: Topic :: Database
Classifier: Topic :: Database :: Front-Ends
Requires-Python: >=3.7
License-File: LICENSE
Requires-Dist: sqlalchemy>=1.4
Requires-Dist: requests>=2.25.0
Requires-Dist: sqlparse>=0.4.0
Provides-Extra: dev
Requires-Dist: pytest>=7.0; extra == "dev"
Requires-Dist: pytest-cov>=3.0; extra == "dev"
Requires-Dist: python-dotenv>=0.19.0; extra == "dev"
Dynamic: author
Dynamic: license-file
Dynamic: requires-python
